{
    "availableLanguageIds": [
        "en_US"
    ],
    "defaultLanguageId": "en_US",
    "fields": [
        {
            "label": {
                "en_US": "Länk (intern)"
            },
            "predefinedValue": {
                "en_US": ""
            },
            "style": {
                "en_US": ""
            },
            "tip": {
                "en_US": "Om du vill använda en extern-url istället, lämna detta fält blankt och skriva in extern-url i fältet nedan."
            },
            "dataType": "link-to-page",
            "fieldNamespace": "ddm",
            "indexType": "keyword",
            "localizable": true,
            "name": "navigationItems",
            "readOnly": false,
            "repeatable": true,
            "required": false,
            "showLabel": true,
            "type": "ddm-link-to-page",
            "nestedFields": [
                {
                    "label": {
                        "en_US": "Länk (extern)"
                    },
                    "predefinedValue": {
                        "en_US": ""
                    },
                    "style": {
                        "en_US": ""
                    },
                    "tip": {
                        "en_US": "Lämna blank om du använder en intern länk."
                    },
                    "dataType": "string",
                    "indexType": "keyword",
                    "localizable": true,
                    "name": "externalLink",
                    "readOnly": false,
                    "repeatable": false,
                    "required": false,
                    "showLabel": true,
                    "type": "text",
                    "nestedFields": [
                        {
                            "label": {
                                "en_US": "Länktext"
                            },
                            "predefinedValue": {
                                "en_US": ""
                            },
                            "style": {
                                "en_US": ""
                            },
                            "tip": {
                                "en_US": "Behöver endast fyllas i om du använder en en extern länk."
                            },
                            "dataType": "string",
                            "indexType": "keyword",
                            "localizable": true,
                            "name": "linkText",
                            "readOnly": false,
                            "repeatable": false,
                            "required": false,
                            "showLabel": true,
                            "type": "text"
                        },
                        {
                            "label": {
                                "en_US": "Ikonklass"
                            },
                            "predefinedValue": {
                                "en_US": ""
                            },
                            "style": {
                                "en_US": ""
                            },
                            "tip": {
                                "en_US": "Om du använder en intern-url sätter du en ikon klass här (likt när du redigerar en sida och väljer ikonClass på \"Egna fält\" för sidan)."
                            },
                            "dataType": "string",
                            "indexType": "keyword",
                            "localizable": true,
                            "name": "iconClass",
                            "readOnly": false,
                            "repeatable": false,
                            "required": false,
                            "showLabel": true,
                            "type": "text"
                        }
                    ]
                },
                {
                    "label": {
                        "en_US": "Target"
                    },
                    "options": [
                        {
                            "value": "none",
                            "label": {
                                "en_US": "Normal"
                            }
                        },
                        {
                            "value": "_BLANK",
                            "label": {
                                "en_US": "Nytt Fönster (_BLANK)"
                            }
                        }
                    ],
                    "predefinedValue": {
                        "en_US": [
                            ""
                        ]
                    },
                    "style": {
                        "en_US": ""
                    },
                    "tip": {
                        "en_US": ""
                    },
                    "dataType": "string",
                    "indexType": "keyword",
                    "localizable": true,
                    "multiple": false,
                    "name": "linkTarget",
                    "readOnly": false,
                    "repeatable": false,
                    "required": false,
                    "showLabel": true,
                    "type": "select"
                }
            ]
        }
    ]
}
